pyautomation/__init__.py
pyautomation/app_usage.py
pyautomation/autogui.py
pyautomation/displayinfo.py
pyautomation/msuiauto.py
pyautomation/pyauto.py
pyautomation/pyautovision.py
pyautomation/modules/__init__.py
pyautomation/modules/mss/__init__.py
pyautomation/modules/mss/__main__.py
pyautomation/modules/mss/base.py
pyautomation/modules/mss/darwin.py
pyautomation/modules/mss/exception.py
pyautomation/modules/mss/factory.py
pyautomation/modules/mss/linux.py
pyautomation/modules/mss/models.py
pyautomation/modules/mss/screenshot.py
pyautomation/modules/mss/tools.py
pyautomation/modules/mss/windows.py
pyautomation/modules/pyautogui/__init__.py
pyautomation/modules/pyautogui/pyautogui/__init__.py
pyautomation/modules/pyautogui/pyautogui/__main__.py
pyautomation/modules/pyautogui/pyautogui/_pyautogui_java.py
pyautomation/modules/pyautogui/pyautogui/_pyautogui_osx.py
pyautomation/modules/pyautogui/pyautogui/_pyautogui_win.py
pyautomation/modules/pyautogui/pyautogui/_pyautogui_x11.py
pyautomation/modules/screeninfo/__init__.py
pyautomation/modules/screeninfo/__main__.py
pyautomation/modules/screeninfo/common.py
pyautomation/modules/screeninfo/mytest.py
pyautomation/modules/screeninfo/screeninfo.py
pyautomation/modules/screeninfo/util.py
pyautomation/modules/screeninfo/enumerators/__init__.py
pyautomation/modules/screeninfo/enumerators/cygwin.py
pyautomation/modules/screeninfo/enumerators/drm.py
pyautomation/modules/screeninfo/enumerators/osx.py
pyautomation/modules/screeninfo/enumerators/windows.py
pyautomation/modules/screeninfo/enumerators/xinerama.py
pyautomation/modules/screeninfo/enumerators/xrandr.py
pyautomation/tools/__init__.py
pyautomation/tools/project_structure.py
pyautomation/tools/utils.py
tests/__init__.py
tests/child_uiautomation.py
tests/debug_pyautovision.py
tests/feature_matching.py
tests/msuiauto.py
tests/test_capture.py
tests/test_executor.py
tests/test_pyauto.py
tests/test_pyauto2.py
tests/test_version.py
tests/usage_pyauto.py
python_automation-0.6.4.dist-info/LICENSE
python_automation-0.6.4.dist-info/METADATA
python_automation-0.6.4.dist-info/WHEEL
python_automation-0.6.4.dist-info/top_level.txt
python_automation-0.6.4.dist-info/RECORD
