Metadata-Version: 2.1
Name: python-automation
Version: 0.6.4
Summary: window automation package
Home-page: https://github.com/changgwak/python-automation
Author: changgwak
Author-email: iamtony.ca@gmail.com
Keywords: pyauto,rpa,python rpa,python automation,window selenium,pyautomation,autoclick
Classifier: Programming Language :: Python :: 3.10
Classifier: Programming Language :: Python :: 3.11
Classifier: Programming Language :: Python :: 3.12
Requires-Python: >=3.10
License-File: LICENSE
Requires-Dist: opencv-python
Requires-Dist: numpy
Requires-Dist: pillow
Requires-Dist: pywin32
Requires-Dist: comtypes
Requires-Dist: PyQt5
Requires-Dist: pyscreeze
Requires-Dist: pyyaml
Requires-Dist: aiofiles
Requires-Dist: pydantic
Requires-Dist: injector
Requires-Dist: APScheduler
Requires-Dist: dataclasses
Requires-Dist: python-dotenv
